cwtraces/Lab_4_3.cwp
cwtraces/__init__.py
cwtraces/lab2_1b_passwords_full.p
cwtraces/lab3_1_textin.npy
cwtraces/lab3_1_traces.npy
cwtraces/lab3_3_textin.npy
cwtraces/lab3_3_traces.npy
cwtraces/lab4_1_key.npy
cwtraces/lab4_1_textin.npy
cwtraces/lab4_1_traces.npy
cwtraces/lab4_2_key.npy
cwtraces/lab4_2_textin.npy
cwtraces/lab4_2_traces.npy
cwtraces/lab_4_3.zip
cwtraces/Lab_4_3_data/traces/2024.09.17-17.23.08_0keylist.npy
cwtraces/Lab_4_3_data/traces/2024.09.17-17.23.08_0knownkey.npy
cwtraces/Lab_4_3_data/traces/2024.09.17-17.23.08_0textin.npy
cwtraces/Lab_4_3_data/traces/2024.09.17-17.23.08_0textout.npy
cwtraces/Lab_4_3_data/traces/2024.09.17-17.23.08_0traces.npy
cwtraces/Lab_4_3_data/traces/config_2024.09.17-17.23.08_0.cfg
cwtraces/__pycache__/__init__.cpython-39.pyc
cwtraces-0.0.1.dist-info/METADATA
cwtraces-0.0.1.dist-info/WHEEL
cwtraces-0.0.1.dist-info/top_level.txt
cwtraces-0.0.1.dist-info/RECORD
